.VERSION
AUTHORS.rst
CONTRIBUTING.rst
HISTORY.rst
LICENSE
MANIFEST.in
Pipfile
Pipfile.lock
README.rst
USAGE.rst
dev-requirements.txt
requirements.txt
setup.cfg
setup.py
cheflib/.VERSION
cheflib/AUTHORS.rst
cheflib/CONTRIBUTING.rst
cheflib/HISTORY.rst
cheflib/LICENSE
cheflib/Pipfile
cheflib/Pipfile.lock
cheflib/README.rst
cheflib/USAGE.rst
cheflib/__init__.py
cheflib/_version.py
cheflib/cheflib.py
cheflib/cheflibexceptions.py
cheflib/configuration.py
cheflib/dev-requirements.txt
cheflib/requirements.txt
cheflib.egg-info/PKG-INFO
cheflib.egg-info/SOURCES.txt
cheflib.egg-info/dependency_links.txt
cheflib.egg-info/not-zip-safe
cheflib.egg-info/requires.txt
cheflib.egg-info/top_level.txt
cheflib/__pycache__/__init__.cpython-39.pyc
cheflib/__pycache__/_version.cpython-39.pyc
cheflib/__pycache__/cheflib.cpython-39.pyc
cheflib/__pycache__/cheflibexceptions.cpython-39.pyc
cheflib/__pycache__/configuration.cpython-39.pyc
cheflib/entities/__init__.py
cheflib/entities/base.py
cheflib/entities/client.py
cheflib/entities/client_key.py
cheflib/entities/cookbook.py
cheflib/entities/databag.py
cheflib/entities/databagitem.py
cheflib/entities/environment.py
cheflib/entities/node.py
cheflib/entities/role.py
cheflib/entities/__pycache__/__init__.cpython-39.pyc
cheflib/entities/__pycache__/base.cpython-39.pyc
cheflib/entities/__pycache__/client.cpython-39.pyc
cheflib/entities/__pycache__/client_key.cpython-39.pyc
cheflib/entities/__pycache__/cookbook.cpython-39.pyc
cheflib/entities/__pycache__/databag.cpython-39.pyc
cheflib/entities/__pycache__/databagitem.cpython-39.pyc
cheflib/entities/__pycache__/environment.cpython-39.pyc
cheflib/entities/__pycache__/node.cpython-39.pyc
cheflib/entities/__pycache__/role.cpython-39.pyc
docs/Makefile
docs/authors.rst
docs/conf.py
docs/contributing.rst
docs/history.rst
docs/index.rst
docs/installation.rst
docs/readme.rst
docs/usage.rst
tests/test_cheflib.py