Metadata-Version: 2.1
Name: cheflib
Version: 0.0.4
Summary: A Chef server api python library
Home-page: https://github.com/schubergphilis/cheflib.git
Author: Daan de Goede
Author-email: ddegoede@schubergphilis.com
License: Apache Software License
Keywords: cheflib
Classifier: Development Status :: 4 - Beta
Classifier: Intended Audience :: Developers
Classifier: License :: OSI Approved :: Apache Software License
Classifier: Natural Language :: English
Classifier: Programming Language :: Python :: 3.9
License-File: LICENSE
License-File: AUTHORS.rst
Requires-Dist: chefsessionlib==0.1.1
Requires-Dist: pycryptodome==3.20.0; python_version >= "2.7" and python_version not in "3.0, 3.1, 3.2, 3.3, 3.4"
Requires-Dist: rsa==4.9; python_version >= "3.6" and python_version < "4"
